proto_topy.py
proto_topy-1.0.5.dist-info/LICENSE
proto_topy-1.0.5.dist-info/METADATA
proto_topy-1.0.5.dist-info/WHEEL
proto_topy-1.0.5.dist-info/top_level.txt
proto_topy-1.0.5.dist-info/RECORD
