Metadata-Version: 2.1
Name: proto-topy
Version: 1.0.5
Summary: Yet another tool that compiles .proto strings and import the outcome Python modules.
License: MIT License
Project-URL: homepage, https://github.com/decitre/python-proto-topy
Classifier: Intended Audience :: Developers
Classifier: License :: OSI Approved :: MIT License
Classifier: Programming Language :: Python :: 3
Classifier: Programming Language :: Python :: 3 :: Only
Classifier: Programming Language :: Python :: 3.8
Classifier: Programming Language :: Python :: 3.9
Classifier: Programming Language :: Python :: 3.10
Classifier: Programming Language :: Python :: 3.11
Classifier: Programming Language :: Python :: 3.12
Classifier: Programming Language :: Python :: Implementation :: CPython
Classifier: Operating System :: OS Independent
Requires-Python: >=3.8
License-File: LICENSE
Requires-Dist: protobuf>=3.20.3
Provides-Extra: ci
Requires-Dist: virtualenv>=16.6.0; extra == "ci"
Requires-Dist: pip>=19.1.1; extra == "ci"
Requires-Dist: setuptools>=18.0.1; extra == "ci"
Requires-Dist: six>=1.14.0; extra == "ci"
Requires-Dist: tox>=4.12.1; extra == "ci"
Requires-Dist: tox-gh>=1.2; extra == "ci"
Provides-Extra: dev
Requires-Dist: pytest; extra == "dev"
Requires-Dist: pytest-recording; extra == "dev"
Requires-Dist: urllib3<2; extra == "dev"
Requires-Dist: bumpver; extra == "dev"
Requires-Dist: black; extra == "dev"
Requires-Dist: ruff; extra == "dev"
Requires-Dist: pre-commit; extra == "dev"
Requires-Dist: tox; extra == "dev"
Requires-Dist: build; extra == "dev"
Requires-Dist: twine; extra == "dev"
Requires-Dist: setuptools; extra == "dev"
